toucans/__init__.py
toucans/completion_config.py
toucans/prompt_function.py
toucans/utils.py
toucans-0.0.14.dist-info/METADATA
toucans-0.0.14.dist-info/WHEEL
toucans-0.0.14.dist-info/RECORD
